[{"array_sizes": {"xA": 360, "xB": 100, "xC": 940, "yC": 60, "xD": 820, "yD": 50, "zD": 250, "xE": 770}, "distances": {"d1": 0}, "type": "int", "init_with": "random", "loop_nest_level": 2, "unique_arrays_write": ["A[xA]", "B[xB]", "C[xC,yC]", "D[xD,yD,zD]", "E[xE]"], "unique_arrays_read": ["A[xA]", "B[xB]", "C[xC,yC]", "D[xD,yD,zD]", "E[xE]"], "dependencies": {"FLOW": [{"array_name": "D", "distance": "(3,2,4,)", "mix_in": "num_val"}], "ANTI": [{"array_name": "E", "distance": "(0,)", "mix_in": "random"}], "OUTPUT": [{"array_name": "A", "distance": "(5,)", "mix_in": "random"}], "INPUT": [{"array_name": "C", "distance": "(5,2,)", "mix_in": "num_val"}]}}]