[{"array_sizes": {"xA": 610, "yA": 620, "zA": 530, "xB": 100, "yB": 350, "xC": 210, "yC": 880, "xD": 560, "xE": 950, "yE": 310, "zE": 640}, "distances": {"d1": 0}, "type": "float", "init_with": "random", "loop_nest_level": 4, "unique_arrays_write": ["A[xA,yA,zA]", "B[xB,yB]", "C[xC,yC]", "D[xD]", "E[xE,yE,zE]"], "unique_arrays_read": ["A[xA,yA,zA]", "B[xB,yB]", "C[xC,yC]", "D[xD]", "E[xE,yE,zE]"], "dependencies": {"FLOW": [{"array_name": "B", "distance": "(0,5,)", "mix_in": "num_val"}, {"array_name": "A", "distance": "(4,1,5,)", "mix_in": "num_val"}], "OUTPUT": [{"array_name": "E", "distance": "(2,3,4,)", "mix_in": "random"}], "INPUT": [{"array_name": "D", "distance": "(2,)", "mix_in": "num_val"}]}}]