[{"array_sizes": {"xA": 850, "yA": 710, "zA": 680, "xB": 950, "xC": 960, "yC": 700, "zC": 350, "xD": 350, "yD": 70, "zD": 880, "xE": 470}, "distances": {"d1": 0}, "type": "int", "init_with": "random", "loop_nest_level": 3, "unique_arrays_write": ["A[xA,yA,zA]", "B[xB]", "C[xC,yC,zC]", "D[xD,yD,zD]", "E[xE]"], "unique_arrays_read": ["A[xA,yA,zA]", "B[xB]", "C[xC,yC,zC]", "D[xD,yD,zD]", "E[xE]"], "dependencies": {"FLOW": [{"array_name": "C", "distance": "(4,3,5,)", "mix_in": "num_val"}], "OUTPUT": [{"array_name": "C", "distance": "(1,5,5,)", "mix_in": "num_val"}, {"array_name": "E", "distance": "(3,)", "mix_in": "random"}, {"array_name": "D", "distance": "(2,1,5,)", "mix_in": "num_val"}], "INPUT": [{"array_name": "A", "distance": "(4,5,1,)", "mix_in": "random"}, {"array_name": "E", "distance": "(5,)", "mix_in": "random"}]}}]