[{"array_sizes": {"xA": 670, "yA": 720, "xB": 300, "yB": 750, "zB": 940, "xC": 1000, "xD": 520}, "distances": {"d1": 0}, "type": "int", "init_with": "ones", "loop_nest_level": 2, "unique_arrays_write": ["A[xA,yA]", "B[xB,yB,zB]", "C[xC]", "D[xD]"], "unique_arrays_read": ["A[xA,yA]", "B[xB,yB,zB]", "C[xC]", "D[xD]"], "dependencies": {"FLOW": [{"array_name": "C", "distance": "(5,)", "mix_in": "num_val"}], "OUTPUT": [{"array_name": "C", "distance": "(0,)", "mix_in": "random"}, {"array_name": "A", "distance": "(4,4,)", "mix_in": "num_val"}, {"array_name": "A", "distance": "(5,0,)", "mix_in": "random"}, {"array_name": "D", "distance": "(2,)", "mix_in": "num_val"}], "INPUT": [{"array_name": "A", "distance": "(0,4,)", "mix_in": "num_val"}, {"array_name": "C", "distance": "(5,)", "mix_in": "random"}]}}]