[{"array_sizes": {"xA": 410, "xB": 640, "yB": 740, "zB": 650}, "distances": {"d1": 0}, "type": "float", "init_with": "zeros", "loop_nest_level": 3, "unique_arrays_write": ["A[xA]", "B[xB,yB,zB]"], "unique_arrays_read": ["A[xA]", "B[xB,yB,zB]"], "dependencies": {"FLOW": [{"array_name": "B", "distance": "(1,1,3,)", "mix_in": "num_val"}], "ANTI": [{"array_name": "B", "distance": "(3,3,3,)", "mix_in": "random"}, {"array_name": "A", "distance": "(5,)", "mix_in": "random"}, {"array_name": "B", "distance": "(5,5,1,)", "mix_in": "num_val"}], "OUTPUT": [{"array_name": "B", "distance": "(0,1,4,)", "mix_in": "num_val"}, {"array_name": "B", "distance": "(4,1,5,)", "mix_in": "num_val"}], "INPUT": [{"array_name": "A", "distance": "(0,)", "mix_in": "num_val"}]}}]