[{"array_sizes": {"xA": 660, "yA": 250, "xB": 540, "xC": 540, "yC": 90, "zC": 180, "xD": 890, "yD": 770, "xE": 880, "yE": 10}, "distances": {"d1": 0}, "type": "double", "init_with": "random", "loop_nest_level": 1, "unique_arrays_write": ["A[xA,yA]", "B[xB]", "C[xC,yC,zC]", "D[xD,yD]", "E[xE,yE]"], "unique_arrays_read": ["A[xA,yA]", "B[xB]", "C[xC,yC,zC]", "D[xD,yD]", "E[xE,yE]"], "dependencies": {"FLOW": [{"array_name": "B", "distance": "(5,)", "mix_in": "num_val"}], "ANTI": [{"array_name": "D", "distance": "(0,5,)", "mix_in": "num_val"}], "OUTPUT": [{"array_name": "A", "distance": "(4,4,)", "mix_in": "random"}, {"array_name": "D", "distance": "(1,1,)", "mix_in": "random"}], "INPUT": [{"array_name": "A", "distance": "(0,3,)", "mix_in": "num_val"}]}}]