[{"array_sizes": {"xA": 330, "yA": 890, "zA": 100, "xB": 90, "xC": 10, "xD": 620, "yD": 420, "xE": 930, "yE": 620}, "distances": {"d1": 0}, "type": "float", "init_with": "ones", "loop_nest_level": 2, "unique_arrays_write": ["A[xA,yA,zA]", "B[xB]", "C[xC]", "D[xD,yD]", "E[xE,yE]"], "unique_arrays_read": ["A[xA,yA,zA]", "B[xB]", "C[xC]", "D[xD,yD]", "E[xE,yE]"], "dependencies": {"FLOW": [{"array_name": "E", "distance": "(3,3,)", "mix_in": "random"}, {"array_name": "C", "distance": "(4,)", "mix_in": "num_val"}], "OUTPUT": [{"array_name": "C", "distance": "(2,)", "mix_in": "random"}], "INPUT": [{"array_name": "B", "distance": "(2,)", "mix_in": "num_val"}]}}]