[{"array_sizes": {"xA": 860, "yA": 380, "xB": 690, "yB": 890, "xC": 900, "yC": 430, "xD": 850, "yD": 610}, "distances": {"d1": 0}, "type": "float", "init_with": "random", "loop_nest_level": 3, "unique_arrays_write": ["A[xA,yA]", "B[xB,yB]", "C[xC,yC]", "D[xD,yD]"], "unique_arrays_read": ["A[xA,yA]", "B[xB,yB]", "C[xC,yC]", "D[xD,yD]"], "dependencies": {"OUTPUT": [{"array_name": "B", "distance": "(4,1,)", "mix_in": "num_val"}], "INPUT": [{"array_name": "C", "distance": "(5,2,)", "mix_in": "num_val"}]}}]