[{"array_sizes": {"xA": 290, "yA": 1000, "zA": 420, "xB": 630, "yB": 30, "xC": 470, "yC": 650, "xD": 810, "yD": 870, "xE": 520}, "distances": {"d1": 0}, "type": "double", "init_with": "ones", "loop_nest_level": 1, "unique_arrays_write": ["A[xA,yA,zA]", "B[xB,yB]", "C[xC,yC]", "D[xD,yD]", "E[xE]"], "unique_arrays_read": ["A[xA,yA,zA]", "B[xB,yB]", "C[xC,yC]", "D[xD,yD]", "E[xE]"], "dependencies": {"FLOW": [{"array_name": "C", "distance": "(4,5,)", "mix_in": "num_val"}], "INPUT": [{"array_name": "B", "distance": "(5,5,)", "mix_in": "num_val"}, {"array_name": "D", "distance": "(0,5,)", "mix_in": "random"}]}}]