[{"array_sizes": {"xA": 390, "yA": 540, "zA": 30, "xB": 770, "xC": 280, "xD": 760, "xE": 740}, "distances": {"d1": 0}, "type": "int", "init_with": "zeros", "loop_nest_level": 2, "unique_arrays_write": ["A[xA,yA,zA]", "B[xB]", "C[xC]", "D[xD]", "E[xE]"], "unique_arrays_read": ["A[xA,yA,zA]", "B[xB]", "C[xC]", "D[xD]", "E[xE]"], "dependencies": {"FLOW": [{"array_name": "A", "distance": "(4,0,2,)", "mix_in": "random"}], "OUTPUT": [{"array_name": "D", "distance": "(4,)", "mix_in": "random"}, {"array_name": "A", "distance": "(3,3,2,)", "mix_in": "num_val"}]}}]