[{"array_sizes": {"xA": 760, "xB": 620, "yB": 500, "zB": 150, "xC": 270, "yC": 680, "xD": 170, "yD": 970, "zD": 350, "xE": 820, "yE": 70}, "distances": {"d1": 0}, "type": "int", "init_with": "random", "loop_nest_level": 3, "unique_arrays_write": ["A[xA]", "B[xB,yB,zB]", "C[xC,yC]", "D[xD,yD,zD]", "E[xE,yE]"], "unique_arrays_read": ["A[xA]", "B[xB,yB,zB]", "C[xC,yC]", "D[xD,yD,zD]", "E[xE,yE]"], "dependencies": {"FLOW": [{"array_name": "B", "distance": "(2,3,3,)", "mix_in": "num_val"}, {"array_name": "E", "distance": "(2,5,)", "mix_in": "num_val"}], "ANTI": [{"array_name": "E", "distance": "(5,5,)", "mix_in": "num_val"}, {"array_name": "A", "distance": "(2,)", "mix_in": "num_val"}], "OUTPUT": [{"array_name": "C", "distance": "(5,5,)", "mix_in": "random"}]}}]