[{"array_sizes": {"xA": 950, "yA": 870, "zA": 910, "xB": 310, "yB": 860, "zB": 200, "xC": 180, "xD": 910, "yD": 190}, "distances": {"d1": 0}, "type": "float", "init_with": "ones", "loop_nest_level": 2, "unique_arrays_write": ["A[xA,yA,zA]", "B[xB,yB,zB]", "C[xC]", "D[xD,yD]"], "unique_arrays_read": ["A[xA,yA,zA]", "B[xB,yB,zB]", "C[xC]", "D[xD,yD]"], "dependencies": {"FLOW": [{"array_name": "A", "distance": "(2,5,3,)", "mix_in": "random"}], "ANTI": [{"array_name": "A", "distance": "(1,4,2,)", "mix_in": "num_val"}], "INPUT": [{"array_name": "A", "distance": "(4,3,1,)", "mix_in": "num_val"}, {"array_name": "A", "distance": "(4,5,2,)", "mix_in": "num_val"}]}}]