[{"array_sizes": {"xA": 570, "xB": 860, "yB": 150, "zB": 770, "xC": 490, "yC": 1000, "zC": 230, "xD": 80, "xE": 880}, "distances": {"d1": 0}, "type": "float", "init_with": "random", "loop_nest_level": 1, "unique_arrays_write": ["A[xA]", "B[xB,yB,zB]", "C[xC,yC,zC]", "D[xD]", "E[xE]"], "unique_arrays_read": ["A[xA]", "B[xB,yB,zB]", "C[xC,yC,zC]", "D[xD]", "E[xE]"], "dependencies": {"FLOW": [{"array_name": "E", "distance": "(2,)", "mix_in": "random"}], "ANTI": [{"array_name": "D", "distance": "(0,)", "mix_in": "random"}, {"array_name": "E", "distance": "(0,)", "mix_in": "num_val"}, {"array_name": "C", "distance": "(2,3,3,)", "mix_in": "random"}], "INPUT": [{"array_name": "C", "distance": "(0,4,0,)", "mix_in": "random"}, {"array_name": "E", "distance": "(2,)", "mix_in": "random"}, {"array_name": "A", "distance": "(2,)", "mix_in": "num_val"}]}}]