[{"array_sizes": {"xA": 670, "yA": 290, "zA": 920, "xB": 720, "yB": 580, "zB": 440, "xC": 770, "xD": 280, "yD": 740}, "distances": {"d1": 0}, "type": "float", "init_with": "random", "loop_nest_level": 2, "unique_arrays_write": ["A[xA,yA,zA]", "B[xB,yB,zB]", "C[xC]", "D[xD,yD]"], "unique_arrays_read": ["A[xA,yA,zA]", "B[xB,yB,zB]", "C[xC]", "D[xD,yD]"], "dependencies": {"ANTI": [{"array_name": "D", "distance": "(3,1,)", "mix_in": "num_val"}], "OUTPUT": [{"array_name": "B", "distance": "(4,1,5,)", "mix_in": "num_val"}], "INPUT": [{"array_name": "A", "distance": "(5,3,3,)", "mix_in": "num_val"}]}}]