[{"array_sizes": {"xA": 860, "yA": 930, "zA": 730, "xB": 700, "yB": 720, "xC": 90, "yC": 140, "xD": 530, "xE": 880, "yE": 50}, "distances": {"d1": 0}, "type": "float", "init_with": "random", "loop_nest_level": 1, "unique_arrays_write": ["A[xA,yA,zA]", "B[xB,yB]", "C[xC,yC]", "D[xD]", "E[xE,yE]"], "unique_arrays_read": ["A[xA,yA,zA]", "B[xB,yB]", "C[xC,yC]", "D[xD]", "E[xE,yE]"], "dependencies": {"FLOW": [{"array_name": "B", "distance": "(1,5,)", "mix_in": "random"}], "OUTPUT": [{"array_name": "B", "distance": "(4,0,)", "mix_in": "random"}], "INPUT": [{"array_name": "B", "distance": "(1,5,)", "mix_in": "num_val"}]}}]