[{"array_sizes": {"xA": 240, "yA": 170, "zA": 810, "xB": 60, "xC": 160, "yC": 720, "zC": 850, "xD": 320, "yD": 510, "zD": 640, "xE": 810, "yE": 970, "zE": 870}, "distances": {"d1": 0}, "type": "double", "init_with": "ones", "loop_nest_level": 4, "unique_arrays_write": ["A[xA,yA,zA]", "B[xB]", "C[xC,yC,zC]", "D[xD,yD,zD]", "E[xE,yE,zE]"], "unique_arrays_read": ["A[xA,yA,zA]", "B[xB]", "C[xC,yC,zC]", "D[xD,yD,zD]", "E[xE,yE,zE]"], "dependencies": {"FLOW": [{"array_name": "B", "distance": "(5,)", "mix_in": "random"}], "OUTPUT": [{"array_name": "D", "distance": "(2,5,5,)", "mix_in": "random"}], "INPUT": [{"array_name": "C", "distance": "(3,2,5,)", "mix_in": "random"}]}}]