[{"array_sizes": {"xA": 970, "yA": 880, "xB": 510, "yB": 970, "xC": 770, "yC": 620, "zC": 810, "xD": 340, "yD": 180, "xE": 640, "yE": 440}, "distances": {"d1": 0}, "type": "double", "init_with": "zeros", "loop_nest_level": 3, "unique_arrays_write": ["A[xA,yA]", "B[xB,yB]", "C[xC,yC,zC]", "D[xD,yD]", "E[xE,yE]"], "unique_arrays_read": ["A[xA,yA]", "B[xB,yB]", "C[xC,yC,zC]", "D[xD,yD]", "E[xE,yE]"], "dependencies": {"FLOW": [{"array_name": "D", "distance": "(0,2,)", "mix_in": "num_val"}], "ANTI": [{"array_name": "D", "distance": "(1,0,)", "mix_in": "num_val"}], "OUTPUT": [{"array_name": "C", "distance": "(3,0,2,)", "mix_in": "random"}, {"array_name": "C", "distance": "(2,3,5,)", "mix_in": "num_val"}], "INPUT": [{"array_name": "D", "distance": "(1,0,)", "mix_in": "num_val"}, {"array_name": "E", "distance": "(0,1,)", "mix_in": "random"}]}}]