[{"array_sizes": {"xA": 460, "yA": 240, "xB": 580, "yB": 930, "xC": 250, "yC": 40, "zC": 840}, "distances": {"d1": 0}, "type": "float", "init_with": "random", "loop_nest_level": 2, "unique_arrays_write": ["A[xA,yA]", "B[xB,yB]", "C[xC,yC,zC]"], "unique_arrays_read": ["A[xA,yA]", "B[xB,yB]", "C[xC,yC,zC]"], "dependencies": {"OUTPUT": [{"array_name": "B", "distance": "(3,1,)", "mix_in": "num_val"}, {"array_name": "B", "distance": "(5,2,)", "mix_in": "random"}, {"array_name": "B", "distance": "(0,5,)", "mix_in": "num_val"}], "INPUT": [{"array_name": "B", "distance": "(0,3,)", "mix_in": "num_val"}, {"array_name": "A", "distance": "(5,3,)", "mix_in": "num_val"}]}}]