[{"array_sizes": {"xA": 650, "yA": 250, "xB": 470, "xC": 310, "yC": 110, "xD": 610, "yD": 450, "zD": 100, "xE": 360, "yE": 960}, "distances": {"d1": 0}, "type": "int", "init_with": "random", "loop_nest_level": 1, "unique_arrays_write": ["A[xA,yA]", "B[xB]", "C[xC,yC]", "D[xD,yD,zD]", "E[xE,yE]"], "unique_arrays_read": ["A[xA,yA]", "B[xB]", "C[xC,yC]", "D[xD,yD,zD]", "E[xE,yE]"], "dependencies": {"FLOW": [{"array_name": "B", "distance": "(5,)", "mix_in": "random"}, {"array_name": "A", "distance": "(2,0,)", "mix_in": "random"}], "OUTPUT": [{"array_name": "C", "distance": "(1,3,)", "mix_in": "random"}], "INPUT": [{"array_name": "D", "distance": "(3,4,0,)", "mix_in": "random"}]}}]